gensecureAI/__init__.py
gensecureAI/core.py
gensecureai-0.2.1.dist-info/licenses/LICENSE
gensecureai-0.2.1.dist-info/METADATA
gensecureai-0.2.1.dist-info/WHEEL
gensecureai-0.2.1.dist-info/top_level.txt
gensecureai-0.2.1.dist-info/RECORD
