Metadata-Version: 2.4
Name: gensecureAI
Version: 0.2.1
Summary: AI-powered Python Security Scanner with GUI and Auto-Fix
Author: Jamshaid Basit
Author-email: jamshaidbasit0011@gmail.com
License: MIT
Classifier: Programming Language :: Python :: 3
Classifier: License :: OSI Approved :: MIT License
Classifier: Operating System :: OS Independent
Requires-Python: >=3.9
License-File: LICENSE
Requires-Dist: rich
Requires-Dist: groq
Requires-Dist: python-dotenv
Dynamic: license-file
